{"cameraMode":{"drawMode":0,"name":"Shaded","section":"Shading Mode"},"sceneLighting":false,"audioPlay":false,"sceneViewState":{"m_AlwaysRefresh":false,"showFog":true,"showSkybox":false,"showFlares":true,"showImageEffects":true,"showParticleSystems":true,"showVisualEffectGraphs":true,"m_FxEnabled":true},"in2DMode":false,"pivot":{"x":16.69551658630371,"y":-50.43476867675781,"z":-41.1893310546875},"rotation":{"x":0.008526704274117947,"y":0.8434192538261414,"z":-0.5370425581932068,"w":0.01339479349553585},"size":107.65071868896485,"orthographic":false}