{"cameraMode":{"drawMode":0,"name":"Shaded","section":"Shading Mode"},"sceneLighting":true,"audioPlay":false,"sceneViewState":{"m_AlwaysRefresh":false,"showFog":true,"showSkybox":true,"showFlares":true,"showImageEffects":true,"showParticleSystems":true,"showVisualEffectGraphs":true,"m_FxEnabled":true},"in2DMode":false,"pivot":{"x":175.6043243408203,"y":-1117.573974609375,"z":106.7528076171875},"rotation":{"x":0.6957791447639465,"y":0.0039023584686219694,"z":-0.0037582479417324068,"w":0.7182614207267761},"size":715.7998657226563,"orthographic":false}